build/lib/torchcam/__init__.py
build/lib/torchcam/metrics.py
build/lib/torchcam/utils.py
build/lib/torchcam/version.py
build/lib/torchcam/methods/__init__.py
build/lib/torchcam/methods/_utils.py
build/lib/torchcam/methods/activation.py
build/lib/torchcam/methods/core.py
build/lib/torchcam/methods/gradient.py
torchcam/__init__.py
torchcam/metrics.py
torchcam/utils.py
torchcam/version.py
torchcam/methods/__init__.py
torchcam/methods/_utils.py
torchcam/methods/activation.py
torchcam/methods/core.py
torchcam/methods/gradient.py
torchcam-0.4.0.dist-info/LICENSE
torchcam-0.4.0.dist-info/METADATA
torchcam-0.4.0.dist-info/WHEEL
torchcam-0.4.0.dist-info/top_level.txt
torchcam-0.4.0.dist-info/zip-safe
torchcam-0.4.0.dist-info/RECORD
