Metadata-Version: 2.1
Name: torchcam
Version: 0.4.0
Summary: Class activation maps for your PyTorch CNN models
Author-email: François-Guillaume Fernandez <fg-feedback@protonmail.com>
License:                                  Apache License
Project-URL: documentation, https://frgfm.github.io/torch-cam
Project-URL: repository, https://github.com/frgfm/torch-cam
Project-URL: tracker, https://github.com/frgfm/torch-cam/issues
Project-URL: changelog, https://frgfm.github.io/torch-cam/latest/changelog.html
Keywords: pytorch,deep learning,class activation map,cnn,gradcam
Classifier: Development Status :: 4 - Beta
Classifier: Intended Audience :: Developers
Classifier: Intended Audience :: Science/Research
Classifier: License :: OSI Approved :: Apache Software License
Classifier: Natural Language :: English
Classifier: Operating System :: OS Independent
Classifier: Programming Language :: Python :: 3
Classifier: Programming Language :: Python :: 3.8
Classifier: Programming Language :: Python :: 3.9
Classifier: Programming Language :: Python :: 3.10
Classifier: Programming Language :: Python :: 3.11
Classifier: Topic :: Scientific/Engineering
Classifier: Topic :: Scientific/Engineering :: Mathematics
Classifier: Topic :: Scientific/Engineering :: Artificial Intelligence
Requires-Python: <4,>=3.8
License-File: LICENSE
Requires-Dist: torch<3.0.0,>=2.0.0
Requires-Dist: numpy<2.0.0,>=1.17.2
Requires-Dist: Pillow!=9.2.0,>=8.4.0
Requires-Dist: matplotlib<4.0.0,>=3.7.0
Provides-Extra: test
Requires-Dist: requests<3.0.0,>=2.20.0; extra == "test"
Requires-Dist: torchvision<1.0.0,>=0.15.0; extra == "test"
Requires-Dist: pytest>=7.3.2; extra == "test"
Requires-Dist: pytest-cov<5.0.0,>=3.0.0; extra == "test"
Requires-Dist: pytest-xdist<4.0.0,>=2.0.0; extra == "test"
Requires-Dist: pytest-pretty<2.0.0,>=1.0.0; extra == "test"
Provides-Extra: quality
Requires-Dist: ruff==0.1.0; extra == "quality"
Requires-Dist: mypy==1.5.1; extra == "quality"
Requires-Dist: black==23.3.0; extra == "quality"
Requires-Dist: bandit[toml]<1.8.0,>=1.7.0; extra == "quality"
Requires-Dist: pre-commit<3.0.0,>=2.17.0; extra == "quality"
Provides-Extra: docs
Requires-Dist: sphinx!=3.5.0,>=3.0.0; extra == "docs"
Requires-Dist: furo>=2022.3.4; extra == "docs"
Requires-Dist: sphinxemoji>=0.1.8; extra == "docs"
Requires-Dist: sphinx-copybutton>=0.3.1; extra == "docs"
Requires-Dist: recommonmark>=0.7.1; extra == "docs"
Requires-Dist: sphinx-markdown-tables>=0.0.15; extra == "docs"
Requires-Dist: Jinja2<3.1; extra == "docs"
Provides-Extra: demo
Requires-Dist: streamlit<2.0.0,>=0.65.0; extra == "demo"
Requires-Dist: torchvision<1.0.0,>=0.15.0; extra == "demo"
Provides-Extra: dev
Requires-Dist: requests<3.0.0,>=2.20.0; extra == "dev"
Requires-Dist: torchvision<1.0.0,>=0.15.0; extra == "dev"
Requires-Dist: pytest>=7.3.2; extra == "dev"
Requires-Dist: pytest-cov<5.0.0,>=4.0.0; extra == "dev"
Requires-Dist: pytest-xdist<4.0.0,>=3.0.0; extra == "dev"
Requires-Dist: pytest-pretty<2.0.0,>=1.0.0; extra == "dev"
Requires-Dist: ruff==0.1.0; extra == "dev"
Requires-Dist: mypy==1.5.1; extra == "dev"
Requires-Dist: black==23.3.0; extra == "dev"
Requires-Dist: bandit[toml]<1.8.0,>=1.7.0; extra == "dev"
Requires-Dist: pre-commit<3.0.0,>=2.17.0; extra == "dev"
Requires-Dist: sphinx!=3.5.0,>=3.0.0; extra == "dev"
Requires-Dist: furo>=2022.3.4; extra == "dev"
Requires-Dist: sphinxemoji>=0.1.8; extra == "dev"
Requires-Dist: sphinx-copybutton>=0.3.1; extra == "dev"
Requires-Dist: recommonmark>=0.7.1; extra == "dev"
Requires-Dist: sphinx-markdown-tables>=0.0.15; extra == "dev"
Requires-Dist: Jinja2<3.1; extra == "dev"
